example/ver_water_light/top.v
module top(
	input clk,
	input rst,
	output reg [2:0] led,
	output reg [1:0] count
);
	//reg [1:0] count;
	always @(posedge clk) begin
		if (rst) begin led <= 3'b001; count <= 2'b00; end
		else begin
			if (count == 2'b00) led <= {led[1:0], led[2]};
			count <= (count >= 2'b10 ? 2'b00 : count + 1);
		end
	end
endmodule

example/ver_water_light/waveform.vcd
$version Generated by VerilatedVcd $end
$timescale 1ps $end

 $scope module TOP $end
  $var wire  1 # clk $end
  $var wire  2 & count [1:0] $end
  $var wire  3 % led [2:0] $end
  $var wire  1 $ rst $end
  $scope module top $end
   $var wire  1 # clk $end
   $var wire  2 & count [1:0] $end
   $var wire  3 % led [2:0] $end
   $var wire  1 $ rst $end
  $upscope $end
 $upscope $end
$enddefinitions $end


#0
1#
0$
b010 %
b00 &
#1
0#
#2
1#
b100 %
b01 &
#3
0#
1$
#4
1#
b001 %
b00 &
#5
0#
#6
1#
0$
b010 %
b01 &
#7
0#
#8
1#
b10 &
#9
0#
#10
1#
b00 &
#11
0#
#12
1#
b100 %
b01 &
#13
0#
#14
1#
b10 &
#15
0#
#16
1#
b00 &
#17
0#
#18
1#
b001 %
b01 &
#19
0#
#20
1#
b10 &
#21
0#
#22
1#
b00 &
#23
0#
#24
1#
b010 %
b01 &
#25
0#
#26
1#
b10 &
#27
0#
#28
1#
b00 &
#29
0#
#30
1#
b100 %
b01 &
#31
0#
#32
1#
b10 &
#33
0#
#34
1#
b00 &
#35
0#
#36
1#
b001 %
b01 &
#37
0#
#38
1#
b10 &
#39
0#
#40
1#
b00 &
#41
0#
#42
1#
b010 %
b01 &
#43
0#
#44
1#
b10 &
#45
0#
#46
1#
b00 &
#47
0#
#48
1#
b100 %
b01 &
#49
0#
#50
1#
b10 &
#51
0#
#52
1#
b00 &
#53
0#
#54
1#
b001 %
b01 &
#55
0#
#56
1#
b10 &
#57
0#
#58
1#
b00 &
#59
0#
#60
1#
b010 %
b01 &
#61
0#
#62
1#
b10 &
#63
0#
#64
1#
b00 &
#65
0#
#66
1#
b100 %
b01 &
#67
0#
#68
1#
b10 &
#69
0#
#70
1#
b00 &
#71
0#
#72
1#
b001 %
b01 &
#73
0#
#74
1#
b10 &
#75
0#
#76
1#
b00 &
#77
0#
#78
1#
b010 %
b01 &
#79
0#
#80
1#
b10 &
#81
0#
#82
1#
b00 &
#83
0#
#84
1#
b100 %
b01 &
#85
0#
#86
1#
b10 &
#87
0#
#88
1#
b00 &
#89
0#
#90
1#
b001 %
b01 &
#91
0#
#92
1#
b10 &
#93
0#
#94
1#
b00 &
#95
0#
#96
1#
b010 %
b01 &
#97
0#
#98
1#
b10 &
