exper_d_circuit/select/MuxKeyInternal.v
module MuxKeyInternal #(NR_KEY = 2, KEY_LEN = 1, DATA_LEN = 1, HAS_DEFAULT = 0) (
	output reg [DATA_LEN-1:0] out,
	input [KEY_LEN-1:0] key,
	input [DATA_LEN-1:0] default_out,
	input [NR_KEY*(KEY_LEN + DATA_LEN)-1:0] lut
);

	localparam PAIR_LEN = KEY_LEN + DATA_LEN;
	wire [PAIR_LEN-1:0] pair_list [NR_KEY-1:0];
	wire [KEY_LEN-1:0] key_list [NR_KEY-1:0];
	wire [DATA_LEN-1:0] data_list [NR_KEY-1:0];

	generate
		for (genvar n = 0; n < NR_KEY; n = n + 1) begin
			assign pair_list[n] = lut[PAIR_LEN*(n+1)-1 : PAIR_LEN*n];
			assign data_list[n] = pair_list[n][DATA_LEN-1:0];
			assign key_list[n]  = pair_list[n][PAIR_LEN-1:DATA_LEN];
		end
	endgenerate

	reg [DATA_LEN-1 : 0] lut_out;
	reg hit;
	integer i;
	always @(*) begin
		lut_out = 0;
		hit = 0;
		for (i = 0; i < NR_KEY; i = i + 1) begin
			lut_out = lut_out | ({DATA_LEN{key == key_list[i]}} & data_list[i]);
			hit = hit | (key == key_list[i]);
		end
		if (!HAS_DEFAULT) out = lut_out;
		else out = (hit ? lut_out : default_out);
	end

endmodule

exper_d_circuit/select/MuxKey.v
`include "MuxKeyInternal.v"

module MuxKey #(NR_KEY = 2, KEY_LEN = 1, DATA_LEN = 1) (
	output [DATA_LEN-1:0] out,
	input [KEY_LEN-1:0] key,
	input [NR_KEY*(KEY_LEN + DATA_LEN)-1:0] lut
);
 	MuxKeyInternal #(NR_KEY, KEY_LEN, DATA_LEN, 0) i0 (out, key, {DATA_LEN{1'b0}}, lut);
endmodule

exper_d_circuit/select/mux241.v
`include "MuxKey.v"

module mux241(
	input [1:0] X0,
	input [1:0] X1,
	input [1:0] X2,
	input [1:0] X3,
	input [1:0] Y,
	output [1:0] F
);
	MuxKey #(4, 2, 2) i0 (F, Y, {
		2'b00, X0,
		2'b01, X1,
		2'b10, X2,
		2'b11, X3
	});

endmodule

exper_d_circuit/select/waveform.vcd
$version Generated by VerilatedVcd $end
$timescale 1ps $end

 $scope module TOP $end
  $var wire  2 6 F [1:0] $end
  $var wire  2 1 X0 [1:0] $end
  $var wire  2 2 X1 [1:0] $end
  $var wire  2 3 X2 [1:0] $end
  $var wire  2 4 X3 [1:0] $end
  $var wire  2 5 Y [1:0] $end
  $scope module mux241 $end
   $var wire  2 6 F [1:0] $end
   $var wire  2 1 X0 [1:0] $end
   $var wire  2 2 X1 [1:0] $end
   $var wire  2 3 X2 [1:0] $end
   $var wire  2 4 X3 [1:0] $end
   $var wire  2 5 Y [1:0] $end
   $scope module i0 $end
    $var wire 32 9 DATA_LEN [31:0] $end
    $var wire 32 9 KEY_LEN [31:0] $end
    $var wire 32 8 NR_KEY [31:0] $end
    $var wire  2 5 key [1:0] $end
    $var wire 16 7 lut [15:0] $end
    $var wire  2 6 out [1:0] $end
    $scope module i0 $end
     $var wire 32 9 DATA_LEN [31:0] $end
     $var wire 32 : HAS_DEFAULT [31:0] $end
     $var wire 32 9 KEY_LEN [31:0] $end
     $var wire 32 8 NR_KEY [31:0] $end
     $var wire 32 8 PAIR_LEN [31:0] $end
     $var wire  2 + data_list[0] [1:0] $end
     $var wire  2 , data_list[1] [1:0] $end
     $var wire  2 - data_list[2] [1:0] $end
     $var wire  2 . data_list[3] [1:0] $end
     $var wire  2 ; default_out [1:0] $end
     $var wire  1 0 hit $end
     $var wire 32 < i [31:0] $end
     $var wire  2 5 key [1:0] $end
     $var wire  2 # key_list[0] [1:0] $end
     $var wire  2 $ key_list[1] [1:0] $end
     $var wire  2 % key_list[2] [1:0] $end
     $var wire  2 & key_list[3] [1:0] $end
     $var wire 16 7 lut [15:0] $end
     $var wire  2 / lut_out [1:0] $end
     $var wire  2 6 out [1:0] $end
     $var wire  4 ' pair_list[0] [3:0] $end
     $var wire  4 ( pair_list[1] [3:0] $end
     $var wire  4 ) pair_list[2] [3:0] $end
     $var wire  4 * pair_list[3] [3:0] $end
    $upscope $end
   $upscope $end
  $upscope $end
 $upscope $end
$enddefinitions $end


#0
b01 #
b01 $
b01 %
b10 &
b0110 '
b0100 (
b0111 )
b0011 *
b10 +
b01 ,
b10 -
b10 .
b01 /
00
b00 1
b00 2
b10 3
b00 4
b00 5
b00 6
b0000010010101100 7
b00000000000000000000000000000100 8
b00000000000000000000000000000010 9
b00000000000000000000000000000000 :
b00 ;
b00000000000000000000000000000100 <
#1
#2
#3
#4
#5
#6
#7
b11 #
b10 $
b00 &
b1111 '
b1001 (
b0110 )
b11 +
b11 .
b11 /
10
b11 1
b10 2
b01 3
b11 4
b11 6
b0011011010011111 7
#8
b1100 '
b1010 (
b0111 )
b0001 *
b00 +
b10 ,
b11 -
b01 .
b01 /
b01 1
b11 2
b10 3
b00 4
b01 6
b0001011110101100 7
#9
b1111 '
b0101 )
b11 +
b01 -
b01 2
b11 4
b0001010110101111 7
#10
b1110 '
b1011 (
b0111 )
b0010 *
b10 +
b11 ,
b11 -
b10 .
b10 /
b10 1
b11 2
b11 3
b10 4
b10 6
b0010011110111110 7
#11
b1100 '
b1000 (
b0110 )
b0000 *
b00 +
b00 ,
b10 -
b00 .
b00 /
b00 1
b10 2
b00 3
b00 4
b00 6
b0000011010001100 7
#12
b1101 '
b1011 (
b0100 )
b0011 *
b01 +
b11 ,
b00 -
b11 .
b11 1
b00 2
b11 3
b01 4
b01 5
b0011010010111101 7
#13
b1111 '
b1010 (
b0110 )
b0010 *
b11 +
b10 ,
b10 -
b10 .
b10 /
b10 1
b10 2
b10 3
b11 4
b10 6
b0010011010101111 7
#14
b1110 '
b1001 (
b0111 )
b0011 *
b10 +
b01 ,
b11 -
b11 .
b11 /
b11 1
b11 2
b01 3
b10 4
b11 6
b0011011110011110 7
#15
b1111 '
b0110 )
b0010 *
b11 +
b10 -
b10 .
b10 /
b10 1
b10 2
b11 4
b10 6
b0010011010011111 7
#16
b1110 '
b1011 (
b0100 )
b0001 *
b10 +
b11 ,
b00 -
b01 .
b00 /
b01 1
b00 2
b11 3
b10 4
b00 6
b0001010010111110 7
#17
b1111 '
b1001 (
b0101 )
b11 +
b01 ,
b01 -
b01 /
b01 2
b01 3
b11 4
b10 5
b01 6
b0001010110011111 7
#18
b1100 '
b1010 (
b0000 *
b00 +
b10 ,
b00 .
b10 /
b00 1
b10 3
b00 4
b10 6
b0000010110101100 7
#19
b1110 '
b1001 (
b0110 )
b0011 *
b10 +
b01 ,
b10 -
b11 .
b01 /
b11 1
b10 2
b01 3
b10 4
b01 6
b0011011010011110 7
#20
b1101 '
b1000 (
b0100 )
b01 +
b00 ,
b00 -
b00 /
b00 2
b00 3
b01 4
b00 6
b0011010010001101 7
#21
b0110 )
b0010 *
b10 -
b10 .
b10 1
b10 2
b0010011010001101 7
#22
b1111 '
b0101 )
b0001 *
b11 +
b01 -
b01 .
b11 /
b01 1
b01 2
b11 4
b11 5
b11 6
b0001010110001111 7
#23
b1101 '
b1010 (
b0000 *
b01 +
b10 ,
b00 .
b01 /
b00 1
b10 3
b01 4
b01 6
b0000010110101101 7
#24
b1111 '
b1000 (
b0001 *
b11 +
b00 ,
b01 .
b11 /
b01 1
b00 3
b11 4
b11 6
b0001010110001111 7
#25
b1010 (
b0010 *
b10 ,
b10 .
b10 1
b10 3
b0010010110101111 7
#26
b1110 '
b1011 (
b0100 )
b10 +
b11 ,
b00 -
b10 /
b00 2
b11 3
b10 4
b10 6
b0010010010111110 7
#27
b1000 (
b0011 *
b00 ,
b11 .
b00 /
00
b11 1
b00 3
b00 5
b00 6
b0011010010001110 7
#28
b1111 '
b1011 (
b0000 *
b11 +
b11 ,
b00 .
10
b00 1
b11 3
b11 4
b00 5
b0000010010111111 7
#29
b1100 '
b1000 (
b0111 )
b0010 *
b00 +
b00 ,
b11 -
b10 .
b10 /
b10 1
b11 2
b00 3
b00 4
b10 6
b0010011110001100 7
#30
b1011 (
b0100 )
b0000 *
b11 ,
b00 -
b00 .
b00 /
b00 1
b00 2
b11 3
b00 6
b0000010010111100 7
#31
b1111 '
b1010 (
b0110 )
b0010 *
b11 +
b10 ,
b10 -
b10 .
b10 /
b10 1
b10 2
b10 3
b11 4
b10 6
b0010011010101111 7
#32
b1110 '
b0011 *
b10 +
b11 .
b11 /
b11 1
b10 4
b11 6
b0011011010101110 7
#33
b1001 (
b0101 )
b01 ,
b01 -
b01 /
b01 2
b01 3
b01 5
b01 6
b0011010110011110 7
#34
b1100 '
b1000 (
b0100 )
b0001 *
b00 +
b00 ,
b00 -
b01 .
b00 /
b01 1
b00 2
b00 3
b00 4
b00 6
b0001010010001100 7
#35
b1101 '
b1010 (
b01 +
b10 ,
b10 3
b01 4
b0001010010101101 7
#36
b1111 '
b1000 (
b0101 )
b11 +
b00 ,
b01 -
b01 /
b01 2
b00 3
b11 4
b01 6
b0001010110001111 7
#37
b1101 '
b1011 (
b0000 *
b01 +
b11 ,
b00 .
b00 1
b11 3
b01 4
b0000010110111101 7
#38
b1111 '
b1001 (
b0111 )
b0001 *
b11 +
b01 ,
b11 -
b01 .
b01 1
b11 2
b01 3
b11 4
b10 5
b0001011110011111 7
#39
b1100 '
b1011 (
b00 +
b11 ,
b11 /
b11 3
b00 4
b11 6
b0001011110111100 7
#40
b1101 '
b1010 (
b0101 )
b01 +
b10 ,
b01 -
b10 /
b01 2
b10 3
b01 4
b10 6
b0001010110101101 7
#41
b1100 '
b1011 (
b0111 )
b0010 *
b00 +
b11 ,
b11 -
b10 .
b11 /
b10 1
b11 2
b11 3
b00 4
b11 6
b0010011110111100 7
#42
b1101 '
b1000 (
b0000 *
b01 +
b00 ,
b00 .
b00 /
b00 1
b00 3
b01 4
b00 6
b0000011110001101 7
#43
b1100 '
b1010 (
b0011 *
b00 +
b10 ,
b11 .
b11 1
b10 3
b00 4
b11 5
b0011011110101100 7
#44
b1101 '
b1000 (
b0000 *
b01 +
b00 ,
b00 .
b01 /
b00 1
b00 3
b01 4
b01 6
b0000011110001101 7
#45
b1010 (
b10 ,
b10 3
b0000011110101101 7
#46
b1111 '
b1001 (
b0010 *
b11 +
b01 ,
b10 .
b11 /
b10 1
b01 3
b11 4
b11 6
b0010011110011111 7
#47
b1100 '
b1000 (
b0100 )
b0011 *
b00 +
b00 ,
b00 -
b11 .
b00 /
b11 1
b00 2
b00 3
b00 4
b00 6
b0011010010001100 7
#48
b1001 (
b0110 )
b0001 *
b01 ,
b10 -
b01 .
00
b01 1
b10 2
b01 3
b00 5
b0001011010011100 7
#49
b1110 '
b1000 (
b0100 )
b0010 *
b10 +
b00 ,
b00 -
b10 .
b10 /
10
b10 1
b00 2
b00 3
b10 4
b00 5
b10 6
b0010010010001110 7
#50
b1111 '
b1011 (
b0011 *
b11 +
b11 ,
b11 .
b11 /
b11 1
b11 3
b11 4
b11 6
b0011010010111111 7
#51
b1100 '
b0101 )
b00 +
b01 -
b01 2
b00 4
b0011010110111100 7
#52
b1001 (
b0111 )
b0000 *
b01 ,
b11 -
b00 .
b00 /
b00 1
b11 2
b01 3
b00 6
b0000011110011100 7
#53
b1101 '
b1010 (
b0011 *
b01 +
b10 ,
b11 .
b11 /
b11 1
b10 3
b01 4
b11 6
b0011011110101101 7
#54
b1001 (
b0010 *
b01 ,
b10 .
b10 1
b01 3
b01 5
b0010011110011101 7
#55
b1100 '
b1010 (
b0101 )
b0011 *
b00 +
b10 ,
b01 -
b11 .
b01 /
b11 1
b01 2
b10 3
b00 4
b01 6
b0011010110101100 7
#56
b1101 '
b1000 (
b0111 )
b01 +
b00 ,
b11 -
b11 /
b11 2
b00 3
b01 4
b11 6
b0011011110001101 7
#57
b1111 '
b1011 (
b0100 )
b0000 *
b11 +
b11 ,
b00 -
b00 .
b00 /
b00 1
b00 2
b11 3
b11 4
b00 6
b0000010010111111 7
#58
b1100 '
b1010 (
b0110 )
b0001 *
b00 +
b10 ,
b10 -
b01 .
b10 /
b01 1
b10 2
b10 3
b00 4
b10 6
b0001011010101100 7
#59
b1000 (
b0000 *
b00 ,
b00 .
b00 /
b00 1
b00 3
b10 5
b00 6
b0000011010001100 7
#60
b1001 (
b0101 )
b0001 *
b01 ,
b01 -
b01 .
b01 /
b01 1
b01 2
b01 3
b01 6
b0001010110011100 7
#61
b1111 '
b1010 (
b0111 )
b0000 *
b11 +
b10 ,
b11 -
b00 .
b10 /
b00 1
b11 2
b10 3
b11 4
b10 6
b0000011110101111 7
#62
b1101 '
b1000 (
b0010 *
b01 +
b00 ,
b10 .
b00 /
b10 1
b00 3
b01 4
b00 6
b0010011110001101 7
#63
b1111 '
b1001 (
b0110 )
b0000 *
b11 +
b01 ,
b10 -
b00 .
b01 /
b00 1
b10 2
b01 3
b11 4
b01 6
b0000011010011111 7
#64
b1110 '
b0010 *
b10 +
b10 .
b10 /
b10 1
b10 4
b11 5
b10 6
b0010011010011110 7
#65
b1111 '
b0100 )
b11 +
b00 -
b11 /
b00 2
b11 4
b11 6
b0010010010011111 7
#66
b1000 (
b0011 *
b00 ,
b11 .
b11 1
b00 3
b0011010010001111 7
#67
b1011 (
b0010 *
b11 ,
b10 .
b10 1
b11 3
b0010010010111111 7
#68
b1110 '
b1000 (
b10 +
b00 ,
b10 /
b00 3
b10 4
b10 6
b0010010010001110 7
#69
b1101 '
b1001 (
b0110 )
b0011 *
b01 +
b01 ,
b10 -
b11 .
b00 /
00
b11 1
b10 2
b01 3
b01 4
b00 5
b00 6
b0011011010011101 7
#70
b1010 (
b0001 *
b10 ,
b01 .
b01 /
10
b01 1
b10 3
b00 5
b01 6
b0001011010101101 7
#71
b1110 '
b1000 (
b0100 )
b0000 *
b10 +
b00 ,
b00 -
b00 .
b00 /
b00 1
b00 2
b00 3
b10 4
b00 6
b0000010010001110 7
#72
b1100 '
b0101 )
b0010 *
b00 +
b01 -
b10 .
b10 /
b10 1
b01 2
b00 4
b10 6
b0010010110001100 7
#73
b1101 '
b0110 )
b01 +
b10 -
b10 2
b01 4
b0010011010001101 7
#74
b1100 '
b0100 )
b00 +
b00 -
b00 2
b00 4
b0010010010001100 7
#75
b1110 '
b1011 (
b0111 )
b0000 *
b10 +
b11 ,
b11 -
b00 .
b11 /
b00 1
b11 2
b11 3
b10 4
b01 5
b11 6
b0000011110111110 7
#76
b1111 '
b1001 (
b11 +
b01 ,
b01 3
b11 4
b0000011110011111 7
#77
b1110 '
b0110 )
b0001 *
b10 +
b10 -
b01 .
b10 /
b01 1
b10 2
b10 4
b10 6
b0001011010011110 7
#78
b1101 '
b1011 (
b0111 )
b0000 *
b01 +
b11 ,
b11 -
b00 .
b11 /
b00 1
b11 2
b11 3
b01 4
b11 6
b0000011110111101 7
#79
b0100 )
b0011 *
b00 -
b11 .
b00 /
b11 1
b00 2
b00 6
b0011010010111101 7
#80
b1111 '
b1010 (
b0001 *
b11 +
b10 ,
b01 .
b10 /
b01 1
b10 3
b11 4
b10 5
b10 6
b0001010010101111 7
#81
b1100 '
b1000 (
b0110 )
b0010 *
b00 +
b00 ,
b10 -
b10 .
b00 /
b10 1
b10 2
b00 3
b00 4
b00 6
b0010011010001100 7
#82
b1110 '
b0100 )
b10 +
b00 -
b00 2
b10 4
b0010010010001110 7
#83
b1100 '
b1001 (
b0111 )
b0000 *
b00 +
b01 ,
b11 -
b00 .
b01 /
b00 1
b11 2
b01 3
b00 4
b01 6
b0000011110011100 7
#84
b1011 (
b0110 )
b0011 *
b11 ,
b10 -
b11 .
b11 /
b11 1
b10 2
b11 3
b11 6
b0011011010111100 7
#85
b1101 '
b0100 )
b0000 *
b01 +
b00 -
b00 .
b01 /
b00 1
b00 2
b01 4
b11 5
b01 6
b0000010010111101 7
#86
b1111 '
b1010 (
b0110 )
b11 +
b10 ,
b10 -
b11 /
b10 2
b10 3
b11 4
b11 6
b0000011010101111 7
#87
b1100 '
b1001 (
b0101 )
b0010 *
b00 +
b01 ,
b01 -
b10 .
b00 /
b10 1
b01 2
b01 3
b00 4
b00 6
b0010010110011100 7
#88
b1111 '
b1011 (
b0111 )
b0001 *
b11 +
b11 ,
b11 -
b01 .
b11 /
b01 1
b11 2
b11 3
b11 4
b11 6
b0001011110111111 7
#89
b0100 )
b00 -
b00 2
b0001010010111111 7
#90
b1100 '
b1001 (
b0111 )
b0000 *
b00 +
b01 ,
b11 -
b00 .
b00 /
00
b00 1
b11 2
b01 3
b00 4
b00 5
b00 6
b0000011110011100 7
#91
b1110 '
b1000 (
b0110 )
b0011 *
b10 +
b00 ,
b10 -
b11 .
b11 /
10
b11 1
b10 2
b00 3
b10 4
b00 5
b11 6
b0011011010001110 7
#92
b1101 '
b1010 (
b0100 )
b0000 *
b01 +
b10 ,
b00 -
b00 .
b00 /
b00 1
b00 2
b10 3
b01 4
b00 6
b0000010010101101 7
#93
b1100 '
b0101 )
b00 +
b01 -
b01 2
b00 4
b0000010110101100 7
#94
b1110 '
b1000 (
b0100 )
b10 +
b00 ,
b00 -
b00 2
b00 3
b10 4
b0000010010001110 7
#95
b1111 '
b1010 (
b0101 )
b0001 *
b11 +
b10 ,
b01 -
b01 .
b01 /
b01 1
b01 2
b10 3
b11 4
b01 6
b0001010110101111 7
#96
b1101 '
b0110 )
b0000 *
b01 +
b10 -
b00 .
b10 /
b00 1
b10 2
b01 4
b01 5
b10 6
b0000011010101101 7
#97
b1110 '
b1000 (
b0010 *
b10 +
b00 ,
b10 .
b10 1
b00 3
b10 4
b0010011010001110 7
#98
b1100 '
b1011 (
b0101 )
b0001 *
b00 +
b11 ,
b01 -
b01 .
b01 /
b01 1
b01 2
b11 3
b00 4
b01 6
b0001010110111100 7
#99
b1010 (
b0111 )
b0000 *
b10 ,
b11 -
b00 .
b11 /
b00 1
b11 2
b10 3
b11 6
b0000011110101100 7
#100
b1001 (
b0101 )
b0011 *
b01 ,
b01 -
b11 .
b01 /
b11 1
b01 2
b01 3
b01 6
b0011010110011100 7
#101
b1110 '
b1000 (
b0111 )
b0010 *
b10 +
b00 ,
b11 -
b10 .
b00 /
b10 1
b11 2
b00 3
b10 4
b10 5
b00 6
b0010011110001110 7
#102
b1101 '
b1001 (
b0100 )
b0011 *
b01 +
b01 ,
b00 -
b11 .
b01 /
b11 1
b00 2
b01 3
b01 4
b01 6
b0011010010011101 7
#103
b1000 (
b0111 )
b0001 *
b00 ,
b11 -
b01 .
b00 /
b01 1
b11 2
b00 3
b00 6
b0001011110001101 7
#104
b1111 '
b1010 (
b0110 )
b11 +
b10 ,
b10 -
b10 /
b10 2
b10 3
b11 4
b10 6
b0001011010101111 7
#105
b1110 '
b0000 *
b10 +
b00 .
b00 1
b10 4
b0000011010101110 7
#106
b1100 '
b0101 )
b00 +
b01 -
b00 /
b01 2
b00 4
b11 5
b00 6
b0000010110101100 7
#107
b1000 (
b00 ,
b00 3
b0000010110001100 7
#108
b0110 )
b0010 *
b10 -
b10 .
b10 1
b10 2
b0010011010001100 7
#109
b1101 '
b1011 (
b0100 )
b0001 *
b01 +
b11 ,
b00 -
b01 .
b01 /
b01 1
b00 2
b11 3
b01 4
b01 6
b0001010010111101 7
#110
b1110 '
b1010 (
b10 +
b10 ,
b10 /
b10 3
b10 4
b10 6
b0001010010101110 7
#111
b1101 '
b1000 (
b0110 )
b0011 *
b01 +
b00 ,
b10 -
b11 .
b00 /
00
b11 1
b10 2
b00 3
b01 4
b00 5
b00 6
b0011011010001101 7
#112
b0000 *
b00 .
10
b00 1
b00 5
b0000011010001101 7
#113
b1011 (
b0001 *
b11 ,
b01 .
b01 /
b01 1
b11 3
b01 6
b0001011010111101 7
#114
b1100 '
b1001 (
b0101 )
b0011 *
b00 +
b01 ,
b01 -
b11 .
b11 /
b11 1
b01 2
b01 3
b00 4
b11 6
b0011010110011100 7
#115
b1000 (
b0010 *
b00 ,
b10 .
b10 /
b10 1
b00 3
b10 6
b0010010110001100 7
#116
b1101 '
b1001 (
b0100 )
b0011 *
b01 +
b01 ,
b00 -
b11 .
b11 /
b11 1
b00 2
b01 3
b01 4
b11 6
b0011010010011101 7
#117
b1010 (
b0000 *
b10 ,
b00 .
b00 /
b00 1
b10 3
b01 5
b00 6
b0000010010101101 7
#118
b1111 '
b1000 (
b11 +
b00 ,
b00 3
b11 4
b0000010010001111 7
#119
b1110 '
b0010 *
b10 +
b10 .
b10 1
b10 4
b0010010010001110 7
#120
b1111 '
b1011 (
b0101 )
b11 +
b11 ,
b01 -
b01 /
b01 2
b11 3
b11 4
b01 6
b0010010110111111 7
#121
b1000 (
b0110 )
b0011 *
b00 ,
b10 -
b11 .
b10 /
b11 1
b10 2
b00 3
b10 6
b0011011010001111 7
#122
b1110 '
b1011 (
b0101 )
b0000 *
b10 +
b11 ,
b01 -
b00 .
b11 /
b00 1
b01 2
b11 3
b10 4
b10 5
b11 6
b0000010110111110 7
#123
b0111 )
b0011 *
b11 -
b11 .
b11 1
b11 2
b0011011110111110 7
#124
b1111 '
b0100 )
b11 +
b00 -
b00 2
b11 4
b0011010010111111 7
#125
b1100 '
b1001 (
b0101 )
b0000 *
b00 +
b01 ,
b01 -
b00 .
b01 /
b00 1
b01 2
b01 3
b00 4
b01 6
b0000010110011100 7
#126
b1111 '
b1011 (
b0001 *
b11 +
b11 ,
b01 .
b11 /
b01 1
b11 3
b11 4
b11 6
b0001010110111111 7
#127
b1010 (
b0100 )
b10 ,
b00 -
b00 2
b10 3
b11 5
b0001010010101111 7
#128
b1100 '
b1011 (
b0101 )
b00 +
b11 ,
b01 -
b00 /
b01 2
b11 3
b00 4
b00 6
b0001010110111100 7
#129
b0111 )
b0000 *
b11 -
b00 .
b00 1
b11 2
b0000011110111100 7
#130
b1010 (
b0110 )
b0001 *
b10 ,
b10 -
b01 .
b01 1
b10 2
b10 3
b0001011010101100 7
#131
b0101 )
b01 -
b01 2
b0001010110101100 7
#132
b1101 '
b1000 (
b0110 )
b01 +
b00 ,
b10 -
00
b10 2
b00 3
b01 4
b00 5
b0001011010001101 7
#133
b1001 (
b0101 )
b0011 *
b01 ,
b01 -
b11 .
b11 /
10
b11 1
b01 2
b01 3
b00 5
b11 6
b0011010110011101 7
#134
b1111 '
b1000 (
b0010 *
b11 +
b00 ,
b10 .
b10 /
b10 1
b00 3
b11 4
b10 6
b0010010110001111 7
#135
b1110 '
b1010 (
b0110 )
b0001 *
b10 +
b10 ,
b10 -
b01 .
b01 /
b01 1
b10 2
b10 3
b10 4
b01 6
b0001011010101110 7
#136
b1100 '
b0101 )
b0000 *
b00 +
b01 -
b00 .
b00 /
b00 1
b01 2
b00 4
b00 6
b0000010110101100 7
#137
b1110 '
b1000 (
b0110 )
b0001 *
b10 +
b00 ,
b10 -
b01 .
b01 /
b01 1
b10 2
b00 3
b10 4
b01 6
b0001011010001110 7
#138
b1010 (
b0000 *
b10 ,
b00 .
b10 /
b00 1
b10 3
b01 5
b10 6
b0000011010101110 7
#139
b1101 '
b0100 )
b01 +
b00 -
b00 /
b00 2
b01 4
b00 6
b0000010010101101 7
#140
b1110 '
b1011 (
b0110 )
b0010 *
b10 +
b11 ,
b10 -
b10 .
b10 /
b10 1
b10 2
b11 3
b10 4
b10 6
b0010011010111110 7
#141
b1101 '
b0100 )
b0011 *
b01 +
b00 -
b11 .
b00 /
b11 1
b00 2
b01 4
b00 6
b0011010010111101 7
#142
b1110 '
b1000 (
b0111 )
b0001 *
b10 +
b00 ,
b11 -
b01 .
b11 /
b01 1
b11 2
b00 3
b10 4
b11 6
b0001011110001110 7
#143
b0010 *
b10 .
b00 /
b10 1
b10 5
b00 6
b0010011110001110 7
#144
b1101 '
b1010 (
b0000 *
b01 +
b10 ,
b00 .
b10 /
b00 1
b10 3
b01 4
b10 6
b0000011110101101 7
#145
b1011 (
b0110 )
b0001 *
b11 ,
b10 -
b01 .
b11 /
b01 1
b10 2
b11 3
b11 6
b0001011010111101 7
#146
b1100 '
b0101 )
b0000 *
b00 +
b01 -
b00 .
b00 1
b01 2
b00 4
b0000010110111100 7
#147
b1010 (
b0110 )
b0010 *
b10 ,
b10 -
b10 .
b10 /
b10 1
b10 2
b10 3
b10 6
b0010011010101100 7
#148
b0101 )
b0000 *
b01 -
b00 .
b00 /
b00 1
b01 2
b11 5
b00 6
b0000010110101100 7
#149
b1111 '
b1001 (
b0001 *
b11 +
b01 ,
b01 .
b11 /
b01 1
b01 3
b11 4
b11 6
b0001010110011111 7
#150
b0110 )
b10 -
b10 2
b0001011010011111 7
#151
b1101 '
b01 +
b01 /
b01 4
b01 6
b0001011010011101 7
#152
b1110 '
b1011 (
b0111 )
b10 +
b11 ,
b11 -
b10 /
b11 2
b11 3
b10 4
b10 6
b0001011110111110 7
#153
b1101 '
b0110 )
b01 +
b10 -
b00 /
00
b10 2
b01 4
b00 5
b00 6
b0001011010111101 7
#154
b1110 '
b1010 (
b0111 )
b0000 *
b10 +
b10 ,
b11 -
b00 .
10
b00 1
b11 2
b10 3
b10 4
b00 5
b0000011110101110 7
#155
b1101 '
b0100 )
b0001 *
b01 +
b00 -
b01 .
b01 /
b01 1
b00 2
b01 4
b01 6
b0001010010101101 7
#156
b1110 '
b1001 (
b0101 )
b10 +
b01 ,
b01 -
b01 2
b01 3
b10 4
b0001010110011110 7
#157
b1111 '
b0111 )
b0010 *
b11 +
b11 -
b10 .
b10 /
b10 1
b11 2
b11 4
b10 6
b0010011110011111 7
#158
b1110 '
b1010 (
b0001 *
b10 +
b10 ,
b01 .
b01 /
b01 1
b10 3
b10 4
b01 6
b0001011110101110 7
#159
b1011 (
b11 ,
b11 /
b11 3
b01 5
b11 6
b0001011110111110 7
#160
b1111 '
b1000 (
b0110 )
b0010 *
b11 +
b00 ,
b10 -
b10 .
b10 /
b10 1
b10 2
b00 3
b11 4
b10 6
b0010011010001111 7
#161
b1101 '
b1001 (
b0111 )
b0001 *
b01 +
b01 ,
b11 -
b01 .
b11 /
b01 1
b11 2
b01 3
b01 4
b11 6
b0001011110011101 7
#162
b1111 '
b1011 (
b0010 *
b11 +
b11 ,
b10 .
b10 1
b11 3
b11 4
b0010011110111111 7
#163
b1100 '
b1001 (
b0101 )
b0011 *
b00 +
b01 ,
b01 -
b11 .
b01 /
b11 1
b01 2
b01 3
b00 4
b01 6
b0011010110011100 7
#164
b1101 '
b1010 (
b0110 )
b0010 *
b01 +
b10 ,
b10 -
b10 .
b10 /
b10 1
b10 2
b10 3
b01 4
b10 5
b10 6
b0010011010101101 7
#165
b1110 '
b1000 (
b0100 )
b0001 *
b10 +
b00 ,
b00 -
b01 .
b00 /
b01 1
b00 2
b00 3
b10 4
b00 6
b0001010010001110 7
#166
b1100 '
b0111 )
b0011 *
b00 +
b11 -
b11 .
b11 1
b11 2
b00 4
b0011011110001100 7
#167
b1101 '
b1010 (
b0100 )
b0010 *
b01 +
b10 ,
b00 -
b10 .
b10 /
b10 1
b00 2
b10 3
b01 4
b10 6
b0010010010101101 7
#168
b1111 '
b1000 (
b0110 )
b11 +
b00 ,
b10 -
b00 /
b10 2
b00 3
b11 4
b00 6
b0010011010001111 7
#169
b1100 '
b0101 )
b0001 *
b00 +
b01 -
b01 .
b01 1
b01 2
b00 4
b11 5
b0001010110001100 7
#170
b1111 '
b1011 (
b0111 )
b0000 *
b11 +
b11 ,
b11 -
b00 .
b11 /
b00 1
b11 2
b11 3
b11 4
b11 6
b0000011110111111 7
#171
b0100 )
b0001 *
b00 -
b01 .
b01 1
b00 2
b0001010010111111 7
#172
b1100 '
b1000 (
b0110 )
b0011 *
b00 +
b00 ,
b10 -
b11 .
b00 /
b11 1
b10 2
b00 3
b00 4
b00 6
b0011011010001100 7
#173
b1101 '
b1011 (
b0101 )
b0010 *
b01 +
b11 ,
b01 -
b10 .
b01 /
b10 1
b01 2
b11 3
b01 4
b01 6
b0010010110111101 7
#174
b1110 '
b1001 (
b0111 )
b0000 *
b10 +
b01 ,
b11 -
b00 .
b00 /
00
b00 1
b11 2
b01 3
b10 4
b00 5
b00 6
b0000011110011110 7
#175
b1011 (
b0011 *
b11 ,
b11 .
b11 /
10
b11 1
b11 3
b00 5
b11 6
b0011011110111110 7
#176
b1001 (
b0100 )
b0001 *
b01 ,
b00 -
b01 .
b01 /
b01 1
b00 2
b01 3
b01 6
b0001010010011110 7
#177
b1010 (
b0110 )
b10 ,
b10 -
b10 2
b10 3
b0001011010101110 7
#178
b1001 (
b01 ,
b01 3
b0001011010011110 7
#179
b1101 '
b1010 (
b0101 )
b0010 *
b01 +
b10 ,
b01 -
b10 .
b10 /
b10 1
b01 2
b10 3
b01 4
b10 6
b0010010110101101 7
#180
b0110 )
b0011 *
b10 -
b11 .
b11 1
b10 2
b01 5
b0011011010101101 7
#181
b1111 '
b0101 )
b11 +
b01 -
b01 /
b01 2
b11 4
b01 6
b0011010110101111 7
#182
b1100 '
b0111 )
b0000 *
b00 +
b11 -
b00 .
b11 /
b00 1
b11 2
b00 4
b11 6
b0000011110101100 7
#183
b1111 '
b0101 )
b0010 *
b11 +
b01 -
b10 .
b01 /
b10 1
b01 2
b11 4
b01 6
b0010010110101111 7
#184
b1001 (
b0111 )
b0001 *
b01 ,
b11 -
b01 .
b11 /
b01 1
b11 2
b01 3
b11 6
b0001011110011111 7
#185
b0100 )
b00 -
b01 /
b00 2
b10 5
b01 6
b0001010010011111 7
#186
b1100 '
b0110 )
b0010 *
b00 +
b10 -
b10 .
b10 1
b10 2
b00 4
b0010011010011100 7
#187
b1110 '
b1010 (
b0111 )
b0011 *
b10 +
b10 ,
b11 -
b11 .
b10 /
b11 1
b11 2
b10 3
b10 4
b10 6
b0011011110101110 7
