exper_d_circuit/exper_03/alu/alu.v
module alu #(n = 4)(
        input [n-1:0]a,
        input [n-1:0]b,
        input [2:0]select,
        output reg [n-1:0]result,
        output overflow
);
        //详细说明比较大小如何比较？
        //01overflow。02out。
        wire [n-1:0]out;
        assign out = a - b;

        wire [n-1:0]bs;
        assign bs = ({4{1'b1}} ^ b) + 1;
        //wire overflow;
        assign overflow = (a[n-1] == bs[n-1]) && (a[n-1] != out[n-1]);

        wire zero;
        assign zero = ~(|(a - b));

        always @(*) begin
                case(select)
                        3'b000:result = a + b;
                        3'b001:result = a - b;
                        3'b010:result = {4{1'b1}} ^ a;
                        3'b011:result = a & b;
                        3'b100:result = a | b;
                        3'b101:result = a ^ b;
                        3'b110:result = {{3{1'b0}}, {out[n-1] ^ overflow}};
                        3'b111:result = zero ? 4'b1 : 4'b0;
                endcase
        end

endmodule

exper_d_circuit/exper_03/alu/waveform.vcd
$version Generated by VerilatedVcd $end
$timescale 1ps $end

 $scope module TOP $end
  $var wire  4 # a [3:0] $end
  $var wire  4 $ b [3:0] $end
  $var wire  1 ' overflow $end
  $var wire  4 & result [3:0] $end
  $var wire  3 % select [2:0] $end
  $scope module alu $end
   $var wire  4 # a [3:0] $end
   $var wire  4 $ b [3:0] $end
   $var wire  4 ) bs [3:0] $end
   $var wire 32 + n [31:0] $end
   $var wire  4 ( out [3:0] $end
   $var wire  1 ' overflow $end
   $var wire  4 & result [3:0] $end
   $var wire  3 % select [2:0] $end
   $var wire  1 * zero $end
  $upscope $end
 $upscope $end
$enddefinitions $end


#1
b0111 #
b0110 $
b000 %
b1101 &
0'
b0001 (
b1010 )
0*
b00000000000000000000000000000100 +
#2
b1001 #
b0011 $
b001 %
b0110 &
1'
b0110 (
b1101 )
#3
b1010 #
b010 %
b0101 &
b0111 (
#4
b0101 $
b011 %
b0000 &
b0101 (
b1011 )
#5
b100 %
b1111 &
#6
b1000 #
b1111 $
b101 %
b0111 &
0'
b1001 (
b0001 )
#7
b0001 #
b110 %
b0000 &
b0010 (
#8
b1010 #
b1010 $
b111 %
b0001 &
b0000 (
b0110 )
1*
#9
b010 %
b0101 &
#10
b0101 $
b100 %
b1111 &
1'
b0101 (
b1011 )
0*
#11
b1100 #
b1001 $
b000 %
b0101 &
0'
b0011 (
b0111 )
#12
b1000 #
b1111 $
b101 %
b0111 &
b1001 (
b0001 )
#13
b1101 #
b1010 $
b000 %
b0011 (
b0110 )
#14
b1011 #
b0010 $
b110 %
b0001 &
b1001 (
b1110 )
#15
b1010 #
b0101 $
b100 %
b1111 &
1'
b0101 (
b1011 )
#16
b1011 #
b1011 $
b111 %
b0001 &
0'
b0000 (
b0101 )
1*
#17
b0011 #
b0110 $
b000 %
b1001 &
b1101 (
b1010 )
0*
#18
b1000 #
b1111 $
b101 %
b0111 &
b1001 (
b0001 )
#19
b1100 #
b0010 $
b000 %
b1110 &
b1010 (
b1110 )
#20
b1010 #
b0101 $
b100 %
b1111 &
1'
b0101 (
b1011 )
#21
b0100 #
b1000 $
b110 %
b0001 &
0'
b1100 (
b1000 )
#22
b1011 #
b001 %
b0011 &
1'
b0011 (
#23
b0111 #
b1101 $
b000 %
b0100 &
b1010 (
b0011 )
#24
b0110 #
b0110 $
b111 %
b0001 &
0'
b0000 (
b1010 )
1*
#25
b1010 #
b0101 $
b100 %
b1111 &
1'
b0101 (
b1011 )
0*
#26
b1110 $
b001 %
b1100 &
0'
b1100 (
b0010 )
#27
b010 %
b0101 &
#28
b0011 #
b0011 $
b110 %
b0000 &
b0000 (
b1101 )
1*
#29
b1111 #
b1001 $
b000 %
b1000 &
b0110 (
b0111 )
0*
#30
b1000 #
b1111 $
b101 %
b0111 &
b1001 (
b0001 )
#31
b1010 #
b0110 $
b000 %
b0000 &
1'
b0100 (
b1010 )
#32
b0010 #
b0010 $
b111 %
b0001 &
0'
b0000 (
b1110 )
1*
#33
b1010 #
b010 %
b0101 &
b1000 (
0*
#34
b1101 #
b0111 $
b001 %
b0110 &
1'
b0110 (
b1001 )
#35
b0001 #
b1000 $
b110 %
b0001 &
0'
b1001 (
b1000 )
#36
b1000 #
b1111 $
b101 %
b0111 &
b0001 )
#37
b0011 #
b1010 $
b000 %
b1101 &
1'
b0110 )
#38
b0101 #
b1101 $
b001 %
b1000 &
b1000 (
b0011 )
#39
b1010 #
b010 %
b0101 &
0'
b1101 (
#40
b0101 #
b0101 $
b111 %
b0001 &
b0000 (
b1011 )
1*
#41
b0111 #
b1000 $
b000 %
b1111 &
b1111 (
b1000 )
0*
#42
b1001 #
b1110 $
b110 %
b0001 &
b1011 (
b0010 )
#43
b0100 #
b1011 $
b000 %
b1111 &
1'
b1001 (
b0101 )
#44
b1010 #
b0101 $
b011 %
b0000 &
b0101 (
b1011 )
#45
b100 %
b1111 &
#46
b0010 #
b1101 $
b001 %
b0101 &
0'
b0011 )
#47
b0110 #
b1011 $
b000 %
b0001 &
1'
b1011 (
b0101 )
#48
b0100 #
b0100 $
b111 %
0'
b0000 (
b1100 )
1*
#49
b0001 $
b110 %
b0000 &
b0011 (
b1111 )
0*
#50
b1010 #
b0101 $
b100 %
b1111 &
1'
b0101 (
b1011 )
#51
b010 %
b0101 &
#52
b011 %
b0000 &
#53
b1110 #
b0010 $
b000 %
0'
b1100 (
b1110 )
#54
b1000 #
b1111 $
b101 %
b0111 &
b1001 (
b0001 )
#55
b1010 #
b0101 $
b100 %
b1111 &
1'
b0101 (
b1011 )
#56
b0100 #
b0100 $
b111 %
b0001 &
0'
b0000 (
b1100 )
1*
#57
b1010 #
b010 %
b0101 &
1'
b0110 (
0*
#58
b0001 #
b0001 $
b001 %
b0000 &
0'
b0000 (
b1111 )
1*
#59
b1101 #
b1100 $
b000 %
b1001 &
b0001 (
b0100 )
0*
#60
b1000 #
b1111 $
b101 %
b0111 &
b1001 (
b0001 )
#61
b0111 #
b0000 $
b000 %
b0111 (
b0000 )
#62
b1001 #
b1110 $
b001 %
b1011 &
b1011 (
b0010 )
#63
b0001 #
b0001 $
b110 %
b0000 &
b0000 (
b1111 )
1*
#64
b111 %
b0001 &
#65
b1010 #
b0101 $
b100 %
b1111 &
1'
b0101 (
b1011 )
0*
#66
b1000 #
b1111 $
b101 %
b0111 &
0'
b1001 (
b0001 )
#67
b1100 #
b0111 $
b000 %
b0011 &
1'
b0101 (
b1001 )
#68
b1010 #
b0101 $
b011 %
b0000 &
b1011 )
#69
b010 %
b0101 &
#70
b1110 #
b0001 $
b110 %
b0001 &
0'
b1101 (
b1111 )
#71
b0111 $
b000 %
b0101 &
1'
b0111 (
b1001 )
#72
b1010 #
b1010 $
b111 %
b0001 &
0'
b0000 (
b0110 )
1*
#73
b1100 #
b1011 $
b000 %
b0111 &
b0001 (
b0101 )
0*
#74
b0110 #
b1111 $
b001 %
b0111 (
b0001 )
#75
b1010 #
b0101 $
b100 %
b1111 &
1'
b0101 (
b1011 )
#76
b011 %
b0000 &
#77
b1000 #
b1100 $
b110 %
b0001 &
0'
b1100 (
b0100 )
#78
b1111 $
b101 %
b0111 &
b1001 (
b0001 )
#79
b1010 #
b1100 $
b000 %
b0110 &
b1110 (
b0100 )
#80
b0000 #
b0000 $
b111 %
b0001 &
b0000 (
b0000 )
1*
#81
b1010 #
b010 %
b0101 &
b1010 (
0*
#82
b1011 #
b1011 $
b001 %
b0000 &
b0000 (
b0101 )
1*
#83
b0010 #
b1111 $
b000 %
b0001 &
b0011 (
b0001 )
0*
#84
b1100 #
b0100 $
b110 %
b1000 (
b1100 )
#85
b1010 #
b0101 $
b100 %
b1111 &
1'
b0101 (
b1011 )
#86
b1100 #
b1000 $
b001 %
b0100 &
b0100 (
b1000 )
#87
b1010 #
b010 %
b0101 &
b0010 (
#88
b1011 #
b1011 $
b111 %
b0001 &
0'
b0000 (
b0101 )
1*
#89
b1100 #
b0010 $
b000 %
b1110 &
b1010 (
b1110 )
0*
#90
b1000 #
b1111 $
b101 %
b0111 &
b1001 (
b0001 )
#91
b1010 #
b1110 $
b110 %
b0001 &
b1100 (
b0010 )
#92
b0101 $
b011 %
b0000 &
1'
b0101 (
b1011 )
#93
b010 %
b0101 &
#94
b0011 #
b1011 $
b001 %
b1000 &
b1000 (
b0101 )
#95
b1010 #
b0101 $
b100 %
b1111 &
b0101 (
b1011 )
#96
b1010 $
b111 %
b0001 &
0'
b0000 (
b0110 )
1*
#97
b000 %
b0100 &
#98
b1011 #
b1001 $
b110 %
b0000 &
b0010 (
b0111 )
0*
#99
b1010 #
b010 %
b0101 &
b0001 (
#100
b0101 $
b100 %
b1111 &
1'
b0101 (
b1011 )
#101
b0001 #
b0110 $
b000 %
b0111 &
0'
b1011 (
b1010 )
#102
b1000 #
b1111 $
b101 %
b1001 (
b0001 )
#103
b0101 #
b1100 $
b000 %
b0001 &
1'
b0100 )
#104
b1100 #
b111 %
0'
b0000 (
1*
#105
b0100 #
b0101 $
b110 %
b1111 (
b1011 )
0*
#106
b1000 #
b1110 $
b001 %
b1010 &
b1010 (
b0010 )
#107
b0001 #
b1001 $
b000 %
1'
b1000 (
b0111 )
#108
b1000 #
b1111 $
b101 %
b0111 &
0'
b1001 (
b0001 )
#109
b1001 #
b1100 $
b000 %
b0101 &
b1101 (
b0100 )
#110
b1010 #
b0101 $
b100 %
b1111 &
1'
b0101 (
b1011 )
#111
b010 %
b0101 &
#112
b1011 #
b1011 $
b111 %
b0001 &
0'
b0000 (
b0101 )
1*
#113
b1000 #
b1001 $
b000 %
b1111 (
b0111 )
0*
#114
b1111 $
b101 %
b0111 &
b1001 (
b0001 )
#115
b1010 #
b0101 $
b100 %
b1111 &
1'
b0101 (
b1011 )
#116
b011 %
b0000 &
#117
b010 %
b0101 &
#118
b1111 #
b001 %
b1010 &
0'
b1010 (
#119
b0001 #
b1011 $
b110 %
b0000 &
b0110 (
b0101 )
#120
b0001 $
b111 %
b0001 &
b0000 (
b1111 )
1*
#121
b0011 #
b0101 $
b000 %
b1000 &
b1110 (
b1011 )
0*
#122
b1111 #
b0111 $
b001 %
b1000 (
b1001 )
#123
b1010 #
b010 %
b0101 &
1'
b0011 (
#124
b0101 $
b011 %
b0000 &
b0101 (
b1011 )
#125
b100 %
b1111 &
#126
b0000 #
b1001 $
b110 %
b0000 &
0'
b0111 (
b0111 )
#127
b0001 #
b1010 $
b000 %
b1011 &
b0110 )
#128
b0101 #
b0101 $
b111 %
b0001 &
b0000 (
b1011 )
1*
#129
b1010 #
b010 %
b0101 &
1'
b0101 (
0*
#130
b100 %
b1111 &
#131
b1011 $
b000 %
b0101 &
0'
b1111 (
b0101 )
#132
b1000 #
b1111 $
b101 %
b0111 &
b1001 (
b0001 )
#133
b1011 #
b0000 $
b110 %
b0001 &
b1011 (
b0000 )
#134
b1000 #
b0111 $
b001 %
1'
b0001 (
b1001 )
#135
b1010 #
b0101 $
b100 %
b1111 &
b0101 (
b1011 )
#136
b0100 #
b0100 $
b111 %
b0001 &
0'
b0000 (
b1100 )
1*
#137
b1101 #
b1111 $
b000 %
b1100 &
b1110 (
b0001 )
0*
#138
b1000 #
b101 %
b0111 &
b1001 (
#139
b0011 #
b1110 $
b000 %
b0001 &
b0101 (
b0010 )
#140
b1000 #
b1100 $
b110 %
b1100 (
b0100 )
#141
b1010 #
b010 %
b0101 &
b1110 (
#142
b1011 #
b0100 $
b001 %
b0111 &
1'
b0111 (
b1100 )
#143
b0101 #
b000 %
b1001 &
0'
b0001 (
#144
b0011 #
b0011 $
b111 %
b0001 &
b0000 (
b1101 )
1*
#145
b1010 #
b0101 $
b100 %
b1111 &
1'
b0101 (
b1011 )
0*
#146
b001 %
b0101 &
#147
b1110 #
b1011 $
b110 %
b0000 &
0'
b0011 (
b0101 )
#148
b1010 #
b0101 $
b011 %
1'
b0101 (
b1011 )
#149
b1001 #
b0011 $
b000 %
b1100 &
b0110 (
b1101 )
#150
b1000 #
b1111 $
b101 %
b0111 &
0'
b1001 (
b0001 )
#151
b1011 #
b0000 $
b000 %
b1011 &
b1011 (
b0000 )
#152
b0100 #
b0100 $
b111 %
b0001 &
b0000 (
b1100 )
1*
#153
b1010 #
b010 %
b0101 &
1'
b0110 (
0*
#154
b0100 #
b0001 $
b110 %
b0000 &
0'
b0011 (
b1111 )
#155
b1010 #
b0101 $
b100 %
b1111 &
1'
b0101 (
b1011 )
#156
b1000 #
b1111 $
b101 %
b0111 &
0'
b1001 (
b0001 )
#157
b1110 #
b1001 $
b000 %
b0101 (
b0111 )
#158
b1100 #
b1010 $
b001 %
b0010 &
b0010 (
b0110 )
#159
b1010 #
b010 %
b0101 &
b0000 (
1*
#160
b0100 #
b0100 $
b111 %
b0001 &
b1100 )
#161
b1100 #
b0010 $
b110 %
b1010 (
b1110 )
0*
#162
b1000 #
b1111 $
b101 %
b0111 &
b1001 (
b0001 )
#163
b1011 #
b0000 $
b000 %
b1011 &
b1011 (
b0000 )
#164
b1010 #
b0101 $
b011 %
b0000 &
1'
b0101 (
b1011 )
#165
b100 %
b1111 &
#166
b1111 #
b1011 $
b001 %
b0100 &
0'
b0100 (
b0101 )
#167
b0011 #
b1101 $
b000 %
b0000 &
b0110 (
b0011 )
#168
b0011 $
b111 %
b0001 &
b0000 (
b1101 )
1*
#169
b0000 #
b1000 $
b000 %
b1000 &
b1000 (
b1000 )
0*
#170
b1010 #
b0101 $
b100 %
b1111 &
1'
b0101 (
b1011 )
#171
b010 %
b0101 &
#172
b011 %
b0000 &
#173
b0111 #
b000 %
b1100 &
0'
b0010 (
#174
b1000 #
b1111 $
b101 %
b0111 &
b1001 (
b0001 )
#175
b1100 #
b1011 $
b110 %
b0000 &
b0001 (
b0101 )
#176
b1111 #
b1111 $
b111 %
b0001 &
b0000 (
b0001 )
1*
#177
b1010 #
b010 %
b0101 &
b1011 (
0*
#178
b0010 #
b1001 $
b001 %
b1001 &
1'
b1001 (
b0111 )
#179
b1010 #
b1011 $
b000 %
b0101 &
0'
b1111 (
b0101 )
#180
b1000 #
b1111 $
b101 %
b0111 &
b1001 (
b0001 )
#181
b1101 #
b0101 $
b000 %
b0010 &
b1000 (
b1011 )
#182
b1011 #
b0001 $
b110 %
b0001 &
b1010 (
b1111 )
#183
b1010 #
b010 %
b0101 &
b1001 (
#184
b1010 $
b111 %
b0001 &
b0000 (
b0110 )
1*
#185
b0101 $
b100 %
b1111 &
1'
b0101 (
b1011 )
0*
#186
b1000 #
b1111 $
b101 %
b0111 &
0'
b1001 (
b0001 )
#187
b1100 #
b000 %
b1011 &
b1101 (
#188
b1010 #
b0101 $
b011 %
b0000 &
1'
b0101 (
b1011 )
#189
b0011 #
b1000 $
b110 %
b0001 &
0'
b1011 (
b1000 )
#190
b1010 #
b0101 $
b100 %
b1111 &
1'
b0101 (
b1011 )
#191
b1001 #
b1000 $
b000 %
b0001 &
b0001 (
b1000 )
#192
b0100 #
b0100 $
b111 %
0'
b0000 (
b1100 )
1*
#193
b1011 #
b0011 $
b000 %
b1110 &
b1000 (
b1101 )
0*
#194
b0101 #
b1010 $
b001 %
b1011 &
1'
b1011 (
b0110 )
#195
b1010 #
b0101 $
b100 %
b1111 &
b0101 (
b1011 )
#196
b1110 #
b1000 $
b110 %
b0001 &
b0110 (
b1000 )
#197
b1000 #
b0010 $
b000 %
b1010 &
b1110 )
#198
b1111 $
b101 %
b0111 &
0'
b1001 (
b0001 )
#199
b0000 $
b000 %
b1000 &
b1000 (
b0000 )
#200
b1001 #
b1001 $
b111 %
b0001 &
b0000 (
b0111 )
1*
