exper_d_circuit/exper_02/pre_encode83.v
module pre_encode83(
        input [7:0]x,
        input en,
        output reg t,
        output reg [2:0]y
);
        always @(x or en) begin
                if(en) begin
                        casez(x)
                                8'b0000_0001: begin
                                        y = 3'b000; 
                                        t = 1'b1;
                                end
                                8'b0000_001?: begin
                                        y = 3'b001; 
                                        t = 1'b1;
                                end
                                8'b0000_01??: begin
                                        y = 3'b010; 
                                        t = 1'b1;
                                end
                                8'b0000_1???: begin
                                        y = 3'b011; 
                                        t = 1'b1;
                                end
                                8'b0001_????: begin
                                        y = 3'b100; 
                                        t = 1'b1;
                                end
                                8'b001?_????: begin
                                        y = 3'b101; 
                                        t = 1'b1;
                                end
                                8'b01??_????: begin
                                        y = 3'b110; 
                                        t = 1'b1;
                                end
                                8'b1???_????: begin
                                        y = 3'b111; 
                                        t = 1'b1;
                                end
                                default: begin
                                        y = 3'b000; 
                                        t = 1'b0;
                                end
                        endcase
                end
                else begin
                        y = 3'b000; 
                        t = 1'b0;
                end
        end

endmodule

exper_d_circuit/exper_02/waveform.vcd
$version Generated by VerilatedVcd $end
$timescale 1ps $end

 $scope module TOP $end
  $var wire  1 $ en $end
  $var wire  1 % t $end
  $var wire  8 # x [7:0] $end
  $var wire  3 & y [2:0] $end
  $scope module pre_encode83 $end
   $var wire  1 $ en $end
   $var wire  1 % t $end
   $var wire  8 # x [7:0] $end
   $var wire  3 & y [2:0] $end
  $upscope $end
 $upscope $end
$enddefinitions $end


#0
b01100111 #
0$
0%
b000 &
#1
#2
#3
#4
#5
b01101001 #
1$
1%
b110 &
#6
#7
#8
#9
#10
b01010001 #
#11
#12
#13
#14
#15
b01001010 #
0$
0%
b000 &
#16
#17
#18
#19
#20
b00101001 #
1$
1%
b101 &
#21
#22
#23
#24
#25
b10111010 #
b111 &
#26
#27
#28
#29
#30
b11110010 #
#31
#32
#33
#34
#35
b11100011 #
0$
0%
b000 &
#36
#37
#38
#39
#40
b01111100 #
#41
#42
#43
#44
#45
b01010100 #
#46
#47
#48
#49
#50
b00011011 #
#51
#52
#53
#54
#55
b11100111 #
1$
1%
b111 &
#56
#57
#58
#59
#60
b01110110 #
0$
0%
b000 &
#61
#62
#63
#64
#65
b00101110 #
1$
1%
b101 &
#66
#67
#68
#69
#70
b00110011 #
#71
#72
#73
#74
#75
b11001001 #
0$
0%
b000 &
#76
#77
#78
#79
#80
b01100110 #
#81
#82
#83
#84
#85
b00001101 #
1$
1%
b011 &
#86
#87
#88
#89
#90
b00110001 #
0$
0%
b000 &
#91
#92
#93
#94
#95
b10100011 #
#96
#97
#98
#99
#100
b00100101 #
1$
1%
b101 &
#101
#102
#103
#104
#105
b00000101 #
b010 &
#106
#107
#108
#109
#110
b01011000 #
b110 &
#111
#112
#113
#114
#115
b01011110 #
0$
0%
b000 &
#116
#117
#118
#119
#120
b10101011 #
#121
#122
#123
#124
#125
b11001101 #
#126
#127
#128
#129
#130
b10011011 #
#131
#132
#133
#134
#135
b01010100 #
1$
1%
b110 &
#136
#137
#138
#139
#140
b00001110 #
0$
0%
b000 &
#141
#142
#143
#144
#145
b01110100 #
1$
1%
b110 &
#146
#147
#148
#149
#150
b00100001 #
b101 &
#151
#152
#153
#154
#155
b11011100 #
b111 &
#156
#157
#158
#159
#160
b01110000 #
b110 &
#161
#162
#163
#164
#165
b00111110 #
b101 &
#166
#167
#168
#169
#170
b01000001 #
b110 &
#171
#172
#173
#174
#175
b11111100 #
b111 &
#176
#177
#178
#179
#180
b00111110 #
b101 &
#181
#182
#183
#184
#185
b01111110 #
b110 &
#186
#187
#188
#189
#190
b11101010 #
0$
0%
b000 &
#191
#192
#193
#194
#195
b01101011 #
