exper_d_circuit/exper_02/nixie_decode47.v
module nixie_decode47(
        input [3:0]x,
        output reg [6:0]y
);
        always @(x) begin
                case(x)
                        4'b0000: y = 7'b011_1111;//0
                        4'b0001: y = 7'b000_0110;
                        4'b0010: y = 7'b101_1011;
                        4'b0011: y = 7'b100_1111;//3
                        4'b0100: y = 7'b110_0110;
                        4'b0101: y = 7'b110_1101;
                        4'b0110: y = 7'b111_1101;//6
                        4'b0111: y = 7'b000_0111;
                        default: y = 7'b111_1111;
                endcase
        end

endmodule

exper_d_circuit/exper_02/pre_encode83.v
module pre_encode83(
        input [7:0]x,
        input en,
        output reg t,
        output reg [2:0]y
);
        always @(x or en) begin
                if(en) begin
                        casez(x)
                                8'b0000_0001: y = 3'b000; c = 1'b1;
                                8'b0000_001?: y = 3'b001; c = 1'b1;
                                8'b0000_01??: y = 3'b010; c = 1'b1;
                                8'b0000_1???: y = 3'b011; c = 1'b1;
                                8'b0001_????: y = 3'b100; c = 1'b1;
                                8'b001?_????: y = 3'b101; c = 1'b1;
                                8'b01??_????: y = 3'b110; c = 1'b1;
                                8'b1???_????: y = 3'b111; c = 1'b1;
                                default: y = 3'b000; c = 1'b0;
                        endcase
                end
                else y = 3'b000; c = 1'b0;
        end

endmodule

exper_d_circuit/exper_02/top.v
`include "pre_encode83.v"
`include "nixie_decode47.v"

module top(
        input [7:0]x,
        input en,
        output reg t,
        output reg [6:0]y
);
        wire [2:0]numb;

        pre_encode83 u_pre_encode83(
                .x(x),
                .en(en),
                .t(t),
                .y(numb)
        );
        nixie_decode47 u_nixie_decode47(
                .x({1'b0, numb}),
                .y(y)
        );

endmodule

exper_d_circuit/exper_02/waveform.vcd
$version Generated by VerilatedVcd $end
$timescale 1ps $end

 $scope module TOP $end
  $var wire  1 $ en $end
  $var wire  1 % t $end
  $var wire  8 # x [7:0] $end
  $var wire  7 & y [6:0] $end
  $scope module top $end
   $var wire  1 $ en $end
   $var wire  3 ' numb [2:0] $end
   $var wire  1 % t $end
   $var wire  8 # x [7:0] $end
   $var wire  7 & y [6:0] $end
   $scope module u_nixie_decode47 $end
    $var wire  4 ( x [3:0] $end
    $var wire  7 & y [6:0] $end
   $upscope $end
   $scope module u_pre_encode83 $end
    $var wire  1 $ en $end
    $var wire  1 % t $end
    $var wire  8 # x [7:0] $end
    $var wire  3 ' y [2:0] $end
   $upscope $end
  $upscope $end
 $upscope $end
$enddefinitions $end


#0
b01100111 #
1$
1%
b1111101 &
b110 '
b0110 (
#1
#2
#3
#4
#5
b11000110 #
b0000111 &
b111 '
b0111 (
#6
#7
#8
#9
#10
b01101001 #
b1111101 &
b110 '
b0110 (
#11
#12
#13
#14
#15
b01110011 #
#16
#17
#18
#19
#20
b01010001 #
#21
#22
#23
#24
#25
b11111111 #
b0000111 &
b111 '
b0111 (
#26
#27
#28
#29
#30
b01001010 #
b1111101 &
b110 '
b0110 (
#31
#32
#33
#34
#35
b11101100 #
b0000111 &
b111 '
b0111 (
#36
#37
#38
#39
#40
b00101001 #
b1101101 &
b101 '
b0101 (
#41
#42
#43
#44
#45
b11001101 #
b0000111 &
b111 '
b0111 (
#46
#47
#48
#49
#50
b10111010 #
#51
#52
#53
#54
#55
b10101011 #
#56
#57
#58
#59
#60
b11110010 #
#61
#62
#63
#64
#65
b11111011 #
#66
#67
#68
#69
#70
b11100011 #
#71
#72
#73
#74
#75
b01000110 #
b1111101 &
b110 '
b0110 (
#76
#77
#78
#79
#80
b01111100 #
#81
#82
#83
#84
#85
b11000010 #
b0000111 &
b111 '
b0111 (
#86
#87
#88
#89
#90
b01010100 #
b1111101 &
b110 '
b0110 (
#91
#92
#93
#94
#95
b11111000 #
b0000111 &
b111 '
b0111 (
#96
#97
#98
#99
#100
b00011011 #
b1100110 &
b100 '
b0100 (
#101
#102
#103
#104
#105
b11101000 #
b0000111 &
b111 '
b0111 (
#106
#107
#108
#109
#110
b11100111 #
#111
#112
#113
#114
#115
b10001101 #
#116
#117
#118
#119
#120
b01110110 #
b1111101 &
b110 '
b0110 (
#121
#122
#123
#124
#125
b01011010 #
#126
#127
#128
#129
#130
b00101110 #
b1101101 &
b101 '
b0101 (
#131
#132
#133
#134
#135
b01100011 #
b1111101 &
b110 '
b0110 (
#136
#137
#138
#139
#140
b00110011 #
b1101101 &
b101 '
b0101 (
#141
#142
#143
#144
#145
b10011111 #
b0000111 &
b111 '
b0111 (
#146
#147
#148
#149
#150
b11001001 #
#151
#152
#153
#154
#155
b10011010 #
#156
#157
#158
#159
#160
b01100110 #
b1111101 &
b110 '
b0110 (
#161
#162
#163
#164
#165
b00110010 #
b1101101 &
b101 '
b0101 (
#166
#167
#168
#169
#170
b00001101 #
b1001111 &
b011 '
b0011 (
#171
#172
#173
#174
#175
b10110111 #
b0000111 &
b111 '
b0111 (
#176
#177
#178
#179
#180
b00110001 #
b1101101 &
b101 '
b0101 (
#181
#182
#183
#184
#185
b01011000 #
b1111101 &
b110 '
b0110 (
#186
#187
#188
#189
#190
b10100011 #
b0000111 &
b111 '
b0111 (
#191
#192
#193
#194
#195
b01011010 #
b1111101 &
b110 '
b0110 (
