exper_d_circuit/exper_03/add_sub_32/add32.v
/*32位加法器*/
//注意：此处a和b不区分为补码or原码
//仅对其进行加法运算处理。
//例如对于补码：
//1,异号运算后，out_flower始终为0,而out_c则可能0或1
//2,同正号运算，out_flower可能为1,而out_c则始终为0
//3,同负号运算，out_flower可能为1,而out_c则始终为1
module add32(
        input [31:0] a,
        input [31:0] b,
        output [31:0] out,
        output out_c,
        output out_flower
);
        assign {out_c, out} = a + b;
        assign out_flower = (a[31] == b[31]) && (out[31] != a[31]);

endmodule

exper_d_circuit/exper_03/add_sub_32/add_sub_32.v
/*32位加减运算器*/
//注意：此处以a与b为原码
`include "add32.v"

module add_sub_32(
        input [31:0] a,
        input [31:0] b,
        input select,
        output [31:0] result,
        output c,
        output overflow,
        output zero
);
        wire [31:0] bs;
        assign bs = select ? (~b + 32'b1) : b;
        wire [31:0]resultb;
        add32 u_add32(
                .a(a),
                .b(bs),
                .out(resultb),
                .out_c(c),
                .out_flower(overflow)
        );
        assign zero = ~(|result);
        assign result = resultb[31] ? (~resultb + 32'b1) : resultb;

endmodule

exper_d_circuit/exper_03/add_sub_32/waveform.vcd
$version Generated by VerilatedVcd $end
$timescale 1ps $end

 $scope module TOP $end
  $var wire 32 # a [31:0] $end
  $var wire 32 $ b [31:0] $end
  $var wire  1 ' c $end
  $var wire  1 ( overflow $end
  $var wire 32 & result [31:0] $end
  $var wire  1 % select $end
  $var wire  1 ) zero $end
  $scope module add_sub_32 $end
   $var wire 32 # a [31:0] $end
   $var wire 32 $ b [31:0] $end
   $var wire 32 * bs [31:0] $end
   $var wire  1 ' c $end
   $var wire  1 ( overflow $end
   $var wire 32 & result [31:0] $end
   $var wire 32 + resultb [31:0] $end
   $var wire  1 % select $end
   $var wire  1 ) zero $end
   $scope module u_add32 $end
    $var wire 32 # a [31:0] $end
    $var wire 32 * b [31:0] $end
    $var wire 32 + out [31:0] $end
    $var wire  1 ' out_c $end
    $var wire  1 ( out_flower $end
   $upscope $end
  $upscope $end
 $upscope $end
$enddefinitions $end


#0
b00000000000000000000000001110011 #
b00000000000000000000000001010001 $
1%
b00000000000000000000000000100010 &
1'
0(
0)
b11111111111111111111111110101111 *
b00000000000000000000000000100010 +
#1
#2
b00000000000000000000000011001101 #
b00000000000000000000000010111010 $
b00000000000000000000000000010011 &
b11111111111111111111111101000110 *
b00000000000000000000000000010011 +
#3
#4
b00000000000000000000000001000110 #
b00000000000000000000000001111100 $
0%
b00000000000000000000000011000010 &
0'
b00000000000000000000000001111100 *
b00000000000000000000000011000010 +
#5
#6
b00000000000000000000000011101000 #
b00000000000000000000000011100111 $
1%
b00000000000000000000000000000001 &
1'
b11111111111111111111111100011001 *
b00000000000000000000000000000001 +
#7
#8
b00000000000000000000000001110110 #
b00000000000000000000000001011010 $
0%
b00000000000000000000000011010000 &
0'
b00000000000000000000000001011010 *
b00000000000000000000000011010000 +
#9
#10
b00000000000000000000000001100011 #
b00000000000000000000000000110011 $
1%
b00000000000000000000000000110000 &
1'
b11111111111111111111111111001101 *
b00000000000000000000000000110000 +
#11
#12
b00000000000000000000000011001001 #
b00000000000000000000000010011010 $
0%
b00000000000000000000000101100011 &
0'
b00000000000000000000000010011010 *
b00000000000000000000000101100011 +
#13
#14
b00000000000000000000000000110010 #
b00000000000000000000000000001101 $
1%
b00000000000000000000000000100101 &
1'
b11111111111111111111111111110011 *
b00000000000000000000000000100101 +
#15
#16
b00000000000000000000000001011010 #
b00000000000000000000000000100101 $
b00000000000000000000000000110101 &
b11111111111111111111111111011011 *
b00000000000000000000000000110101 +
#17
#18
b00000000000000000000000000000101 #
b00000000000000000000000000010111 $
0%
b00000000000000000000000000011100 &
0'
b00000000000000000000000000010111 *
b00000000000000000000000000011100 +
#19
#20
b00000000000000000000000011101001 #
b00000000000000000000000001011110 $
b00000000000000000000000101000111 &
b00000000000000000000000001011110 *
b00000000000000000000000101000111 +
#21
#22
b00000000000000000000000011000110 #
b00000000000000000000000010011011 $
b00000000000000000000000101100001 &
b00000000000000000000000010011011 *
b00000000000000000000000101100001 +
#23
#24
b00000000000000000000000001010100 #
b00000000000000000000000000010001 $
b00000000000000000000000001100101 &
b00000000000000000000000000010001 *
b00000000000000000000000001100101 +
#25
#26
b00000000000000000000000010000010 #
b00000000000000000000000001110100 $
1%
b00000000000000000000000000001110 &
1'
b11111111111111111111111110001100 *
b00000000000000000000000000001110 +
#27
#28
b00000000000000000000000000100001 #
b00000000000000000000000000111101 $
0%
b00000000000000000000000001011110 &
0'
b00000000000000000000000000111101 *
b00000000000000000000000001011110 +
#29
#30
b00000000000000000000000010000111 #
b00000000000000000000000001110000 $
1%
b00000000000000000000000000010111 &
1'
b11111111111111111111111110010000 *
b00000000000000000000000000010111 +
#31
#32
b00000000000000000000000000111110 #
b00000000000000000000000000000001 $
0%
b00000000000000000000000000111111 &
0'
b00000000000000000000000000000001 *
b00000000000000000000000000111111 +
#33
#34
b00000000000000000000000010010111 #
b00000000000000000000000011101010 $
b00000000000000000000000110000001 &
b00000000000000000000000011101010 *
b00000000000000000000000110000001 +
#35
#36
b00000000000000000000000000111000 #
b00000000000000000000000001011100 $
b00000000000000000000000010010100 &
b00000000000000000000000001011100 *
b00000000000000000000000010010100 +
#37
#38
b00000000000000000000000011101100 #
b00000000000000000000000010110000 $
1%
b00000000000000000000000000111100 &
1'
b11111111111111111111111101010000 *
b00000000000000000000000000111100 +
#39
#40
b00000000000000000000000011111011 #
b00000000000000000000000000110010 $
b00000000000000000000000011001001 &
b11111111111111111111111111001110 *
b00000000000000000000000011001001 +
#41
#42
b00000000000000000000000000111100 #
b00000000000000000000000001010100 $
0%
b00000000000000000000000010010000 &
0'
b00000000000000000000000001010100 *
b00000000000000000000000010010000 +
#43
#44
b00000000000000000000000000011000 #
b00000000000000000000000011011011 $
b00000000000000000000000011110011 &
b00000000000000000000000011011011 *
b00000000000000000000000011110011 +
#45
#46
b00000000000000000000000000000010 #
b00000000000000000000000000011010 $
b00000000000000000000000000011100 &
b00000000000000000000000000011010 *
b00000000000000000000000000011100 +
#47
#48
b00000000000000000000000001000011 #
b00000000000000000000000011111011 $
b00000000000000000000000100111110 &
b00000000000000000000000011111011 *
b00000000000000000000000100111110 +
#49
#50
b00000000000000000000000010101010 #
b00000000000000000000000000111010 $
1%
b00000000000000000000000001110000 &
1'
b11111111111111111111111111000110 *
b00000000000000000000000001110000 +
#51
#52
b00000000000000000000000000101001 #
b00000000000000000000000011010001 $
0%
b00000000000000000000000011111010 &
0'
b00000000000000000000000011010001 *
b00000000000000000000000011111010 +
#53
#54
b00000000000000000000000000000101 #
b00000000000000000000000000111100 $
b00000000000000000000000001000001 &
b00000000000000000000000000111100 *
b00000000000000000000000001000001 +
#55
#56
b00000000000000000000000010010100 #
b00000000000000000000000001110101 $
b00000000000000000000000100001001 &
b00000000000000000000000001110101 *
b00000000000000000000000100001001 +
#57
#58
b00000000000000000000000010111110 #
b00000000000000000000000001100001 $
1%
b00000000000000000000000001011101 &
1'
b11111111111111111111111110011111 *
b00000000000000000000000001011101 +
#59
#60
b00000000000000000000000011111001 #
b00000000000000000000000001011100 $
b00000000000000000000000010011101 &
b11111111111111111111111110100100 *
b00000000000000000000000010011101 +
#61
#62
b00000000000000000000000010101000 #
b00000000000000000000000010011001 $
b00000000000000000000000000001111 &
b11111111111111111111111101100111 *
b00000000000000000000000000001111 +
#63
#64
b00000000000000000000000011110001 #
b00000000000000000000000010110011 $
b00000000000000000000000000111110 &
b11111111111111111111111101001101 *
b00000000000000000000000000111110 +
#65
#66
b00000000000000000000000011101111 #
b00000000000000000000000011110111 $
0%
b00000000000000000000000111100110 &
0'
b00000000000000000000000011110111 *
b00000000000000000000000111100110 +
#67
#68
b00000000000000000000000011101001 #
b00000000000000000000000010100001 $
b00000000000000000000000110001010 &
b00000000000000000000000010100001 *
b00000000000000000000000110001010 +
#69
#70
b00000000000000000000000011100101 #
b00000000000000000000000011001010 $
1%
b00000000000000000000000000011011 &
1'
b11111111111111111111111100110110 *
b00000000000000000000000000011011 +
#71
#72
b00000000000000000000000011001011 #
b00000000000000000000000011010000 $
0%
b00000000000000000000000110011011 &
0'
b00000000000000000000000011010000 *
b00000000000000000000000110011011 +
#73
#74
b00000000000000000000000000011111 #
b00000000000000000000000000100011 $
b00000000000000000000000001000010 &
b00000000000000000000000000100011 *
b00000000000000000000000001000010 +
#75
#76
b00000000000000000000000010101000 #
b00000000000000000000000000011100 $
1%
b00000000000000000000000010001100 &
1'
b11111111111111111111111111100100 *
b00000000000000000000000010001100 +
#77
#78
b00000000000000000000000001100100 #
b00000000000000000000000011000101 $
0%
b00000000000000000000000100101001 &
0'
b00000000000000000000000011000101 *
b00000000000000000000000100101001 +
#79
#80
b00000000000000000000000001110011 #
b00000000000000000000000001011010 $
1%
b00000000000000000000000000011001 &
1'
b11111111111111111111111110100110 *
b00000000000000000000000000011001 +
#81
#82
b00000000000000000000000001011110 #
b00000000000000000000000001001011 $
b00000000000000000000000000010011 &
b11111111111111111111111110110101 *
b00000000000000000000000000010011 +
#83
#84
b00000000000000000000000001100011 #
b00000000000000000000000000111011 $
0%
b00000000000000000000000010011110 &
0'
b00000000000000000000000000111011 *
b00000000000000000000000010011110 +
#85
#86
b00000000000000000000000001100100 #
b00000000000000000000000000100100 $
1%
b00000000000000000000000001000000 &
1'
b11111111111111111111111111011100 *
b00000000000000000000000001000000 +
#87
#88
b00000000000000000000000010011110 #
b00000000000000000000000000001001 $
0%
b00000000000000000000000010100111 &
0'
b00000000000000000000000000001001 *
b00000000000000000000000010100111 +
#89
#90
b00000000000000000000000010101010 #
b00000000000000000000000011010100 $
b00000000000000000000000101111110 &
b00000000000000000000000011010100 *
b00000000000000000000000101111110 +
#91
#92
b00000000000000000000000011110010 #
b00000000000000000000000000011011 $
b00000000000000000000000100001101 &
b00000000000000000000000000011011 *
b00000000000000000000000100001101 +
#93
#94
b00000000000000000000000010101111 #
b00000000000000000000000000111011 $
1%
b00000000000000000000000001110100 &
1'
b11111111111111111111111111000101 *
b00000000000000000000000001110100 +
#95
#96
b00000000000000000000000011001101 #
b00000000000000000000000011100011 $
0%
b00000000000000000000000110110000 &
0'
b00000000000000000000000011100011 *
b00000000000000000000000110110000 +
#97
#98
b00000000000000000000000001001000 #
b00000000000000000000000001000111 $
1%
b00000000000000000000000000000001 &
1'
b11111111111111111111111110111001 *
b00000000000000000000000000000001 +
#99
#100
b00000000000000000000000000100010 #
b00000000000000000000000000011001 $
0%
b00000000000000000000000000111011 &
0'
b00000000000000000000000000011001 *
b00000000000000000000000000111011 +
#101
#102
b00000000000000000000000010011011 #
b00000000000000000000000001111101 $
1%
b00000000000000000000000000011110 &
1'
b11111111111111111111111110000011 *
b00000000000000000000000000011110 +
#103
#104
b00000000000000000000000000001011 #
b00000000000000000000000011100001 $
0%
b00000000000000000000000011101100 &
0'
b00000000000000000000000011100001 *
b00000000000000000000000011101100 +
#105
#106
b00000000000000000000000011111000 #
b00000000000000000000000000101001 $
b00000000000000000000000100100001 &
b00000000000000000000000000101001 *
b00000000000000000000000100100001 +
#107
#108
b00000000000000000000000010100100 #
b00000000000000000000000000011011 $
1%
b00000000000000000000000010001001 &
1'
b11111111111111111111111111100101 *
b00000000000000000000000010001001 +
#109
#110
b00000000000000000000000010110101 #
b00000000000000000000000011001010 $
0%
b00000000000000000000000101111111 &
0'
b00000000000000000000000011001010 *
b00000000000000000000000101111111 +
#111
#112
b00000000000000000000000011101000 #
b00000000000000000000000010011000 $
b00000000000000000000000110000000 &
b00000000000000000000000010011000 *
b00000000000000000000000110000000 +
#113
#114
b00000000000000000000000001001101 #
b00000000000000000000000000111101 $
b00000000000000000000000010001010 &
b00000000000000000000000000111101 *
b00000000000000000000000010001010 +
#115
#116
b00000000000000000000000010111100 #
b00000000000000000000000001011111 $
b00000000000000000000000100011011 &
b00000000000000000000000001011111 *
b00000000000000000000000100011011 +
#117
#118
b00000000000000000000000001101100 #
b00000000000000000000000000000101 $
b00000000000000000000000001110001 &
b00000000000000000000000000000101 *
b00000000000000000000000001110001 +
#119
#120
b00000000000000000000000010000110 #
b00000000000000000000000000100001 $
1%
b00000000000000000000000001100101 &
1'
b11111111111111111111111111011111 *
b00000000000000000000000001100101 +
#121
#122
b00000000000000000000000010101010 #
b00000000000000000000000000011010 $
b00000000000000000000000010010000 &
b11111111111111111111111111100110 *
b00000000000000000000000010010000 +
#123
#124
b00000000000000000000000010100010 #
b00000000000000000000000010111110 $
0%
b00000000000000000000000101100000 &
0'
b00000000000000000000000010111110 *
b00000000000000000000000101100000 +
#125
#126
b00000000000000000000000010110101 #
b00000000000000000000000001110011 $
1%
b00000000000000000000000001000010 &
1'
b11111111111111111111111110001101 *
b00000000000000000000000001000010 +
#127
#128
b00000000000000000000000010101111 #
b00000000000000000000000011100010 $
0%
b00000000000000000000000110010001 &
0'
b00000000000000000000000011100010 *
b00000000000000000000000110010001 +
#129
#130
b00000000000000000000000011100100 #
b00000000000000000000000010011110 $
1%
b00000000000000000000000001000110 &
1'
b11111111111111111111111101100010 *
b00000000000000000000000001000110 +
#131
#132
b00000000000000000000000000110010 #
b00000000000000000000000000010101 $
b00000000000000000000000000011101 &
b11111111111111111111111111101011 *
b00000000000000000000000000011101 +
#133
#134
b00000000000000000000000011111101 #
b00000000000000000000000010000010 $
0%
b00000000000000000000000101111111 &
0'
b00000000000000000000000010000010 *
b00000000000000000000000101111111 +
#135
#136
b00000000000000000000000010101001 #
b00000000000000000000000000001000 $
b00000000000000000000000010110001 &
b00000000000000000000000000001000 *
b00000000000000000000000010110001 +
#137
#138
b00000000000000000000000011010100 #
b00000000000000000000000010110010 $
b00000000000000000000000110000110 &
b00000000000000000000000010110010 *
b00000000000000000000000110000110 +
#139
#140
b00000000000000000000000000101001 #
b00000000000000000000000001010100 $
b00000000000000000000000001111101 &
b00000000000000000000000001010100 *
b00000000000000000000000001111101 +
#141
#142
b00000000000000000000000010011010 #
b00000000000000000000000000001010 $
b00000000000000000000000010100100 &
b00000000000000000000000000001010 *
b00000000000000000000000010100100 +
#143
#144
b00000000000000000000000011010101 #
b00000000000000000000000000001110 $
b00000000000000000000000011100011 &
b00000000000000000000000000001110 *
b00000000000000000000000011100011 +
#145
#146
b00000000000000000000000010101000 #
b00000000000000000000000001000100 $
b00000000000000000000000011101100 &
b00000000000000000000000001000100 *
b00000000000000000000000011101100 +
#147
#148
b00000000000000000000000001011011 #
b00000000000000000000000011110011 $
b00000000000000000000000101001110 &
b00000000000000000000000011110011 *
b00000000000000000000000101001110 +
#149
#150
b00000000000000000000000010011011 #
b00000000000000000000000000001001 $
b00000000000000000000000010100100 &
b00000000000000000000000000001001 *
b00000000000000000000000010100100 +
#151
#152
b00000000000000000000000011100101 #
b00000000000000000000000000000110 $
b00000000000000000000000011101011 &
b00000000000000000000000000000110 *
b00000000000000000000000011101011 +
#153
#154
b00000000000000000000000010100011 #
b00000000000000000000000010000100 $
1%
b00000000000000000000000000011111 &
1'
b11111111111111111111111101111100 *
b00000000000000000000000000011111 +
#155
#156
b00000000000000000000000000101101 #
b00000000000000000000000010101101 $
0%
b00000000000000000000000011011010 &
0'
b00000000000000000000000010101101 *
b00000000000000000000000011011010 +
#157
#158
b00000000000000000000000001110110 #
b00000000000000000000000001000111 $
b00000000000000000000000010111101 &
b00000000000000000000000001000111 *
b00000000000000000000000010111101 +
#159
#160
b00000000000000000000000000110010 #
b00000000000000000000000000011100 $
b00000000000000000000000001001110 &
b00000000000000000000000000011100 *
b00000000000000000000000001001110 +
#161
#162
b00000000000000000000000001001010 #
b00000000000000000000000011000100 $
b00000000000000000000000100001110 &
b00000000000000000000000011000100 *
b00000000000000000000000100001110 +
#163
#164
b00000000000000000000000011110110 #
b00000000000000000000000000100000 $
1%
b00000000000000000000000011010110 &
1'
b11111111111111111111111111100000 *
b00000000000000000000000011010110 +
#165
#166
b00000000000000000000000010000101 #
b00000000000000000000000001101100 $
b00000000000000000000000000011001 &
b11111111111111111111111110010100 *
b00000000000000000000000000011001 +
#167
#168
b00000000000000000000000010110010 #
b00000000000000000000000000000111 $
0%
b00000000000000000000000010111001 &
0'
b00000000000000000000000000000111 *
b00000000000000000000000010111001 +
#169
#170
b00000000000000000000000011110100 #
b00000000000000000000000011101100 $
1%
b00000000000000000000000000001000 &
1'
b11111111111111111111111100010100 *
b00000000000000000000000000001000 +
#171
#172
b00000000000000000000000010111001 #
b00000000000000000000000000100000 $
0%
b00000000000000000000000011011001 &
0'
b00000000000000000000000000100000 *
b00000000000000000000000011011001 +
#173
#174
b00000000000000000000000010000110 #
b00000000000000000000000011000011 $
b00000000000000000000000101001001 &
b00000000000000000000000011000011 *
b00000000000000000000000101001001 +
#175
#176
b00000000000000000000000000000101 #
b00000000000000000000000011110001 $
b00000000000000000000000011110110 &
b00000000000000000000000011110001 *
b00000000000000000000000011110110 +
#177
#178
b00000000000000000000000011011001 #
b00000000000000000000000001100111 $
1%
b00000000000000000000000001110010 &
1'
b11111111111111111111111110011001 *
b00000000000000000000000001110010 +
#179
#180
b00000000000000000000000010110111 #
b00000000000000000000000010011001 $
0%
b00000000000000000000000101010000 &
0'
b00000000000000000000000010011001 *
b00000000000000000000000101010000 +
#181
#182
b00000000000000000000000010100011 #
b00000000000000000000000011100011 $
b00000000000000000000000110000110 &
b00000000000000000000000011100011 *
b00000000000000000000000110000110 +
#183
#184
b00000000000000000000000011010011 #
b00000000000000000000000011011001 $
b00000000000000000000000110101100 &
b00000000000000000000000011011001 *
b00000000000000000000000110101100 +
#185
#186
b00000000000000000000000011110111 #
b00000000000000000000000001011110 $
b00000000000000000000000101010101 &
b00000000000000000000000001011110 *
b00000000000000000000000101010101 +
#187
#188
b00000000000000000000000011110010 #
b00000000000000000000000000010000 $
b00000000000000000000000100000010 &
b00000000000000000000000000010000 *
b00000000000000000000000100000010 +
#189
#190
b00000000000000000000000011110110 #
b00000000000000000000000000000101 $
b00000000000000000000000011111011 &
b00000000000000000000000000000101 *
b00000000000000000000000011111011 +
#191
#192
b00000000000000000000000000000001 #
b00000000000000000000000010111110 $
b00000000000000000000000010111111 &
b00000000000000000000000010111110 *
b00000000000000000000000010111111 +
#193
#194
b00000000000000000000000010111100 #
b00000000000000000000000001000100 $
b00000000000000000000000100000000 &
b00000000000000000000000001000100 *
b00000000000000000000000100000000 +
#195
#196
b00000000000000000000000011111010 #
b00000000000000000000000001001001 $
1%
b00000000000000000000000010110001 &
1'
b11111111111111111111111110110111 *
b00000000000000000000000010110001 +
#197
#198
b00000000000000000000000011100110 #
b00000000000000000000000000100011 $
0%
b00000000000000000000000100001001 &
0'
b00000000000000000000000000100011 *
b00000000000000000000000100001001 +
